odoo/addons/mgmtsystem_action/README.rst
odoo/addons/mgmtsystem_action/__init__.py
odoo/addons/mgmtsystem_action/__manifest__.py
odoo/addons/mgmtsystem_action/data/action_sequence.xml
odoo/addons/mgmtsystem_action/data/automated_reminder.xml
odoo/addons/mgmtsystem_action/data/email_template.xml
odoo/addons/mgmtsystem_action/data/mgmtsystem_action_stage.xml
odoo/addons/mgmtsystem_action/demo/mgmtsystem_action.xml
odoo/addons/mgmtsystem_action/i18n/am.po
odoo/addons/mgmtsystem_action/i18n/ca.po
odoo/addons/mgmtsystem_action/i18n/de.po
odoo/addons/mgmtsystem_action/i18n/el_GR.po
odoo/addons/mgmtsystem_action/i18n/es.po
odoo/addons/mgmtsystem_action/i18n/es_CO.po
odoo/addons/mgmtsystem_action/i18n/es_ES.po
odoo/addons/mgmtsystem_action/i18n/fi.po
odoo/addons/mgmtsystem_action/i18n/fr.po
odoo/addons/mgmtsystem_action/i18n/gl.po
odoo/addons/mgmtsystem_action/i18n/hr_HR.po
odoo/addons/mgmtsystem_action/i18n/hu.po
odoo/addons/mgmtsystem_action/i18n/it.po
odoo/addons/mgmtsystem_action/i18n/lv.po
odoo/addons/mgmtsystem_action/i18n/mgmtsystem_action.pot
odoo/addons/mgmtsystem_action/i18n/nb.po
odoo/addons/mgmtsystem_action/i18n/nl.po
odoo/addons/mgmtsystem_action/i18n/nl_NL.po
odoo/addons/mgmtsystem_action/i18n/nn.po
odoo/addons/mgmtsystem_action/i18n/pt.po
odoo/addons/mgmtsystem_action/i18n/pt_BR.po
odoo/addons/mgmtsystem_action/i18n/pt_PT.po
odoo/addons/mgmtsystem_action/i18n/sl.po
odoo/addons/mgmtsystem_action/i18n/sv.po
odoo/addons/mgmtsystem_action/i18n/th.po
odoo/addons/mgmtsystem_action/i18n/tr.po
odoo/addons/mgmtsystem_action/i18n/vi.po
odoo/addons/mgmtsystem_action/models/__init__.py
odoo/addons/mgmtsystem_action/models/mgmtsystem_action.py
odoo/addons/mgmtsystem_action/models/mgmtsystem_action_stage.py
odoo/addons/mgmtsystem_action/models/mgmtsystem_action_tag.py
odoo/addons/mgmtsystem_action/readme/CONFIGURE.rst
odoo/addons/mgmtsystem_action/readme/CONTRIBUTORS.rst
odoo/addons/mgmtsystem_action/readme/DESCRIPTION.rst
odoo/addons/mgmtsystem_action/readme/INSTALL.rst
odoo12_addon_mgmtsystem_action-12.0.1.0.1.dist-info/METADATA
odoo12_addon_mgmtsystem_action-12.0.1.0.1.dist-info/WHEEL
odoo12_addon_mgmtsystem_action-12.0.1.0.1.dist-info/top_level.txt
odoo12_addon_mgmtsystem_action-12.0.1.0.1.dist-info/RECORD
